whatsapp_gpl/__init__.py
whatsapp_gpl/whatsapp_gpl.py
whatsapp_gpl/zeroun_intezar_agler/__init__.py
whatsapp_gpl/zeroun_intezar_agler/zeroun_intezar_agler.py
whatsapp_gpl-0.0.0.dist-info/licenses/LICENSE
whatsapp_gpl-0.0.0.dist-info/METADATA
whatsapp_gpl-0.0.0.dist-info/WHEEL
whatsapp_gpl-0.0.0.dist-info/top_level.txt
whatsapp_gpl-0.0.0.dist-info/RECORD
