Metadata-Version: 2.4
Name: whatsapp-gpl
Version: 0.0.0
Summary: whatsapp_gpl ZerounIntezarAgler
Author: {github_username}
Project-URL: homepage, https://github.com/{github_username}/whatsapp_gpl
Project-URL: repository, https://github.com/{github_username}/whatsapp_gpl
Project-URL: documentation, https://github.com/{github_username}/whatsapp_gpl
License-File: LICENSE
Dynamic: license-file
